shap_on_image/ShapOnImage.py
shap_on_image/__init__.py
shap_on_image/shap_on_image.py
shap_on_image-0.1.1.dist-info/METADATA
shap_on_image-0.1.1.dist-info/WHEEL
shap_on_image-0.1.1.dist-info/top_level.txt
shap_on_image-0.1.1.dist-info/RECORD
