Metadata-Version: 2.1
Name: shap-on-image
Version: 0.1.1
Summary: Display shap values on an image to simplify visualisation
Home-page: https://github.com/philipperbd/shap_on_image
Author: Philippe RAMBAUD
Author-email: p.rambaud@outlook.fr
License: BSD 2-clause
Platform: UNKNOWN
Classifier: Development Status :: 1 - Planning
Classifier: Intended Audience :: Science/Research
Classifier: License :: OSI Approved :: BSD License
Classifier: Operating System :: POSIX :: Linux
Classifier: Programming Language :: Python :: 2
Classifier: Programming Language :: Python :: 2.7
Classifier: Programming Language :: Python :: 3
Classifier: Programming Language :: Python :: 3.4
Classifier: Programming Language :: Python :: 3.5
Classifier: Programming Language :: Python :: 3.8
Requires-Dist: matplotlib
